recap/cli.py
recap/clients/__init__.py
recap/clients/bigquery.py
recap/clients/confluent_registry.py
recap/clients/dbapi.py
recap/clients/fs.py
recap/clients/hive_metastore.py
recap/clients/mysql.py
recap/clients/postgresql.py
recap/clients/snowflake.py
recap/clients/sqlite.py
recap/commands.py
recap/converters/__init__.py
recap/converters/avro.py
recap/converters/bigquery.py
recap/converters/dbapi.py
recap/converters/hive_metastore.py
recap/converters/json_schema.py
recap/converters/mysql.py
recap/converters/postgresql.py
recap/converters/protobuf.py
recap/converters/snowflake.py
recap/converters/sqlite.py
recap/server/__init__.py
recap/server/app.py
recap/server/gateway.py
recap/server/registry.py
recap/settings.py
recap/storage/__init__.py
recap/storage/registry.py
recap/types.py
recap_core-0.14.0.dist-info/METADATA
recap_core-0.14.0.dist-info/WHEEL
recap_core-0.14.0.dist-info/entry_points.txt
recap_core-0.14.0.dist-info/licenses/LICENSE
recap_core-0.14.0.dist-info/RECORD
