Metadata-Version: 2.1
Name: recap-core
Version: 0.14.0
Summary: Recap reads and writes schemas from web services, databases, and schema registries in a standard format
Keywords: avro,data,data catalog,data discovery,data engineering,data governance,data infrastructure,data integration,data pipelines,data quality,devops,devtools,etl,infrastructure,json schema,metadata,protobuf
Author-Email: Chris Riccomini <criccomini@apache.org>
License: MIT
Project-URL: documentation, https://recap.build
Project-URL: homepage, https://recap.build
Project-URL: repository, https://github.com/recap-cloud/recap
Requires-Python: <3.15,>=3.10
Provides-Extra: kafka
Requires-Dist: confluent-kafka[schema-registry]>=2.1.1; extra == "kafka"
Provides-Extra: proto
Requires-Dist: proto-schema-parser>=0.2.0; extra == "proto"
Provides-Extra: hive
Requires-Dist: pymetastore>=0.2.0; extra == "hive"
Provides-Extra: bigquery
Requires-Dist: google-cloud-bigquery>=3.17.2; extra == "bigquery"
Provides-Extra: json
Requires-Dist: referencing>=0.30.0; extra == "json"
Requires-Dist: httpx>=0.24.1; extra == "json"
Provides-Extra: app
Requires-Dist: fastapi>=0.103.0; extra == "app"
Requires-Dist: pydantic>=2.3.0; extra == "app"
Requires-Dist: pydantic-settings>=2.0.3; extra == "app"
Requires-Dist: typer>=0.9.0; extra == "app"
Requires-Dist: uvicorn>=0.23.2; extra == "app"
Requires-Dist: rich>=13.5.2; extra == "app"
Requires-Dist: python-dotenv>=1.0.0; extra == "app"
Requires-Dist: fsspec>=2023.9.2; extra == "app"
Provides-Extra: all
Requires-Dist: recap-core[app,bigquery,hive,json,kafka,proto]; extra == "all"
